pymasmovil/__init__.py
pymasmovil/client.py
pymasmovil/errors/__init__.py
pymasmovil/errors/exceptions.py
pymasmovil/errors/http_error.py
pymasmovil/errors/mm_error.py
pymasmovil/models/__init__.py
pymasmovil/models/account.py
pymasmovil/models/asset.py
pymasmovil/models/contract.py
pymasmovil/models/new_line_request.py
pymasmovil/models/order_item.py
pymasmovil/models/session.py
pymasmovil-0.0.30.dist-info/METADATA
pymasmovil-0.0.30.dist-info/WHEEL
pymasmovil-0.0.30.dist-info/top_level.txt
pymasmovil-0.0.30.dist-info/RECORD
