Metadata-Version: 2.1
Name: pymasmovil
Version: 0.0.30
Summary: Python client for the Más Móvil's B2B API
Home-page: https://gitlab.com/coopdevs/pymasmovil
Author: Coopdevs
Author-email: gerard.funosas@somconnexio.coop
Maintainer: Daniel Palomar, Pau Pérez, Gerard Funosas
License: UNKNOWN
Platform: UNKNOWN
Requires-Dist: requests
